report_monaco/__init__.py
report_monaco/__main__.py
report_monaco/app.py
report_monaco/racing_cli.py
report_monaco/utils.py
report_monaco_road-0.0.9.dist-info/METADATA
report_monaco_road-0.0.9.dist-info/WHEEL
report_monaco_road-0.0.9.dist-info/licenses/LICENSE
report_monaco_road-0.0.9.dist-info/RECORD
