Metadata-Version: 2.1
Name: report_monaco_road
Version: 0.0.9
Summary: Package count unique chars in file or string
Author-email: Botvinko Dmitro <dmitrobottvinko@gmail.com>
License-File: LICENSE
Classifier: License :: OSI Approved :: MIT License
Classifier: Operating System :: OS Independent
Classifier: Programming Language :: Python :: 3
Requires-Python: >=3.8
